targetcli/__init__.py
targetcli/targetcli_shell.py
targetcli/targetclid.py
targetcli/ui_backstore.py
targetcli/ui_node.py
targetcli/ui_root.py
targetcli/ui_target.py
targetcli-3.0.1.dist-info/METADATA
targetcli-3.0.1.dist-info/WHEEL
targetcli-3.0.1.dist-info/entry_points.txt
targetcli-3.0.1.dist-info/licenses/COPYING
targetcli-3.0.1.dist-info/RECORD
