Metadata-Version: 2.4
Name: targetcli
Version: 3.0.1
Summary: A command shell for managing the Linux LIO kernel target
Project-URL: Homepage, http://github.com/open-iscsi/targetcli-fb
Author-email: Andy Grover <agrover@redhat.com>
Maintainer-email: Maurizio Lombardi <mlombard@redhat.com>
License-Expression: Apache-2.0
License-File: COPYING
Classifier: License :: OSI Approved :: Apache Software License
Classifier: Programming Language :: Python :: 3
Classifier: Programming Language :: Python :: 3.9
Classifier: Programming Language :: Python :: 3.12
Requires-Python: >=3.9
Requires-Dist: configshell-fb
Requires-Dist: pygobject
Requires-Dist: rtslib-fb
